lifeincome.py
lifeincome-0.0.1.dist-info/METADATA
lifeincome-0.0.1.dist-info/WHEEL
lifeincome-0.0.1.dist-info/entry_points.txt
lifeincome-0.0.1.dist-info/top_level.txt
lifeincome-0.0.1.dist-info/RECORD
