Metadata-Version: 2.1
Name: lifeincome
Version: 0.0.1
Summary: A package for comparing income and life span
Home-page: https://github.com/JIAN-JUNYANG/-AI-
Author: JIAN
Author-email: s1922012@stu.musashino-u.ac.jp
License: UNKNOWN
Project-URL: data content, https://github.com/JIAN-JUNYANG/-AI-
Platform: UNKNOWN
Classifier: Programming Language :: Python :: 3
Classifier: License :: OSI Approved :: MIT License
Classifier: Operating System :: OS Independent
Requires-Python: >=3.6
